ctc_heatpump/__init__.py
ctc_heatpump/heatpump.py
ctc_heatpump-1.0.0.dist-info/LICENSE
ctc_heatpump-1.0.0.dist-info/METADATA
ctc_heatpump-1.0.0.dist-info/WHEEL
ctc_heatpump-1.0.0.dist-info/top_level.txt
ctc_heatpump-1.0.0.dist-info/RECORD
