Metadata-Version: 2.1
Name: ctc-heatpump
Version: 1.0.0
Summary: Python module for communicating with CTC heat pump by pretending to be a GSM modem
Home-page: https://github.com/bjorkegeek/python_ctc_heatpump
Author: David Björkevik
Author-email: David Björkevik <david@bjorkevik.se>
License: Apache License
Project-URL: Homepage, https://github.com/bjorkegeek/python_ctc_heatpump
Classifier: Programming Language :: Python :: 3
Classifier: License :: OSI Approved :: Apache Software License
Classifier: Operating System :: OS Independent
Requires-Python: >=3.7
License-File: LICENSE
Requires-Dist: aioserial
